cjdnsadmin-0.1.6.data/scripts/peerStats
cjdnsadmin/bencode.py
cjdnsadmin/cjdnsadmin.py
cjdnsadmin/__init__.py
cjdnsadmin-0.1.6.dist-info/metadata.json
cjdnsadmin-0.1.6.dist-info/top_level.txt
cjdnsadmin-0.1.6.dist-info/RECORD
cjdnsadmin-0.1.6.dist-info/DESCRIPTION.rst
cjdnsadmin-0.1.6.dist-info/WHEEL
cjdnsadmin-0.1.6.dist-info/METADATA
