Metadata-Version: 2.0
Name: cjdnsadmin
Version: 0.1.6
Summary: A library to interact with the cjdns Admin Interface
Home-page: https://github.com/thefinn93/cjdnsadmin
Author: Finn Herzfeld
Author-email: finn@seattlemesh.net
License: GPLv3
Keywords: cjdns
Platform: UNKNOWN
Classifier: Development Status :: 3 - Alpha
Classifier: License :: OSI Approved :: GNU Affero General Public License v3
Classifier: Topic :: System :: Networking
